odoo/addons/hr_attendance_modification_tracking/README.rst
odoo/addons/hr_attendance_modification_tracking/__init__.py
odoo/addons/hr_attendance_modification_tracking/__manifest__.py
odoo/addons/hr_attendance_modification_tracking/i18n/es.po
odoo/addons/hr_attendance_modification_tracking/i18n/hr_attendance_modification_tracking.pot
odoo/addons/hr_attendance_modification_tracking/models/__init__.py
odoo/addons/hr_attendance_modification_tracking/models/hr_attendance.py
odoo/addons/hr_attendance_modification_tracking/readme/CONTRIBUTORS.rst
odoo/addons/hr_attendance_modification_tracking/readme/DESCRIPTION.rst
odoo/addons/hr_attendance_modification_tracking/static/description/icon.png
odoo/addons/hr_attendance_modification_tracking/static/description/index.html
odoo/addons/hr_attendance_modification_tracking/views/hr_attendance_view.xml
odoo11_addon_hr_attendance_modification_tracking-11.0.1.0.0.99.dev6.dist-info/METADATA
odoo11_addon_hr_attendance_modification_tracking-11.0.1.0.0.99.dev6.dist-info/WHEEL
odoo11_addon_hr_attendance_modification_tracking-11.0.1.0.0.99.dev6.dist-info/top_level.txt
odoo11_addon_hr_attendance_modification_tracking-11.0.1.0.0.99.dev6.dist-info/RECORD
